accelbyte_py_sdk/api/cloudsave/__init__.py
accelbyte_py_sdk/api/cloudsave/errors.py
accelbyte_py_sdk/api/cloudsave/models/__init__.py
accelbyte_py_sdk/api/cloudsave/models/models_admin_concurrent_record_request.py
accelbyte_py_sdk/api/cloudsave/models/models_admin_game_concurrent_record_request.py
accelbyte_py_sdk/api/cloudsave/models/models_admin_game_record_request.py
accelbyte_py_sdk/api/cloudsave/models/models_admin_game_record_response.py
accelbyte_py_sdk/api/cloudsave/models/models_admin_player_concurrent_record_request.py
accelbyte_py_sdk/api/cloudsave/models/models_admin_player_record_key_info.py
accelbyte_py_sdk/api/cloudsave/models/models_admin_player_record_request.py
accelbyte_py_sdk/api/cloudsave/models/models_admin_player_record_response.py
accelbyte_py_sdk/api/cloudsave/models/models_app_config.py
accelbyte_py_sdk/api/cloudsave/models/models_binary_info_response.py
accelbyte_py_sdk/api/cloudsave/models/models_binary_record_request.py
accelbyte_py_sdk/api/cloudsave/models/models_bulk_get_admin_game_record_request.py
accelbyte_py_sdk/api/cloudsave/models/models_bulk_get_admin_game_record_response.py
accelbyte_py_sdk/api/cloudsave/models/models_bulk_get_admin_player_record_request.py
accelbyte_py_sdk/api/cloudsave/models/models_bulk_get_admin_player_record_response.py
accelbyte_py_sdk/api/cloudsave/models/models_bulk_get_game_binary_record_response.py
accelbyte_py_sdk/api/cloudsave/models/models_bulk_get_game_record_request.py
accelbyte_py_sdk/api/cloudsave/models/models_bulk_get_game_record_response.py
accelbyte_py_sdk/api/cloudsave/models/models_bulk_get_player_binary_record_response.py
accelbyte_py_sdk/api/cloudsave/models/models_bulk_get_player_record_response.py
accelbyte_py_sdk/api/cloudsave/models/models_bulk_get_player_record_size_response.py
accelbyte_py_sdk/api/cloudsave/models/models_bulk_get_player_records_request.py
accelbyte_py_sdk/api/cloudsave/models/models_bulk_update_player_record_by_key_request_detail.py
accelbyte_py_sdk_service_cloudsave-0.25.0.dist-info/METADATA
accelbyte_py_sdk_service_cloudsave-0.25.0.dist-info/WHEEL
accelbyte_py_sdk_service_cloudsave-0.25.0.dist-info/top_level.txt
accelbyte_py_sdk_service_cloudsave-0.25.0.dist-info/RECORD
